PuzzleImage/Board.py
PuzzleImage/PuzzleImage.py
PuzzleImage/SkeltonImage.py
PuzzleImage/WordList.py
PuzzleImage/__init__.py
puzzleimage-2024.0.5.dist-info/LICENSE
puzzleimage-2024.0.5.dist-info/METADATA
puzzleimage-2024.0.5.dist-info/WHEEL
puzzleimage-2024.0.5.dist-info/top_level.txt
puzzleimage-2024.0.5.dist-info/RECORD
