Metadata-Version: 2.1
Name: puzzleimage
Version: 2024.0.5
Summary: A Python library to make puzzle images
Home-page: https://github.com/MakePuzz/puzzleimage
Author: MakePuzz
Author-email: puzzle.hokkaido@gmail.com
Maintainer: MakePuzz
Maintainer-email: puzzle.hokkaido@gmail.com
Classifier: Programming Language :: Python :: 3.6
Classifier: Programming Language :: Python :: 3.7
Classifier: Programming Language :: Python :: 3.8
Classifier: Programming Language :: Python :: 3.9
Classifier: Programming Language :: Python :: 3.10
Classifier: Programming Language :: Python :: 3.11
Classifier: Programming Language :: Python :: 3.12
Classifier: Operating System :: MacOS :: MacOS X
Classifier: Operating System :: Microsoft :: Windows
Requires-Python: >=3.6
License-File: LICENSE
Requires-Dist: numpy
Requires-Dist: matplotlib
Requires-Dist: japanize-matplotlib
